ibapi/__init__.py
ibapi/account_summary_tags.py
ibapi/client.py
ibapi/comm.py
ibapi/commission_report.py
ibapi/common.py
ibapi/connection.py
ibapi/contract.py
ibapi/decoder.py
ibapi/enum_implem.py
ibapi/errors.py
ibapi/execution.py
ibapi/message.py
ibapi/news.py
ibapi/object_implem.py
ibapi/order.py
ibapi/order_condition.py
ibapi/order_state.py
ibapi/orderdecoder.py
ibapi/reader.py
ibapi/scanner.py
ibapi/server_versions.py
ibapi/softdollartier.py
ibapi/tag_value.py
ibapi/ticktype.py
ibapi/utils.py
ibapi/wrapper.py
ibpy_native/__init__.py
ibpy_native/bridge.py
ibpy_native/error.py
ibpy_native/manager.py
ibpy_native/_internal/__init__.py
ibpy_native/_internal/_client.py
ibpy_native/_internal/_global.py
ibpy_native/_internal/_typing.py
ibpy_native/_internal/_wrapper.py
ibpy_native/interfaces/__init__.py
ibpy_native/interfaces/bridge.py
ibpy_native/interfaces/delegates/__init__.py
ibpy_native/interfaces/delegates/account.py
ibpy_native/interfaces/delegates/order.py
ibpy_native/interfaces/listeners/__init__.py
ibpy_native/interfaces/listeners/base.py
ibpy_native/interfaces/listeners/connection.py
ibpy_native/interfaces/listeners/live_ticks.py
ibpy_native/interfaces/listeners/notification.py
ibpy_native/interfaces/listeners/order.py
ibpy_native/models/__init__.py
ibpy_native/models/account.py
ibpy_native/models/order.py
ibpy_native/models/portfolio.py
ibpy_native/models/raw_data.py
ibpy_native/utils/__init__.py
ibpy_native/utils/datatype.py
ibpy_native/utils/finishable_queue.py
ibpy_native-1.0.5.dist-info/LICENSE.md
ibpy_native-1.0.5.dist-info/METADATA
ibpy_native-1.0.5.dist-info/WHEEL
ibpy_native-1.0.5.dist-info/top_level.txt
ibpy_native-1.0.5.dist-info/RECORD
