Metadata-Version: 2.1
Name: ibpy-native
Version: 1.0.5
Summary: Implementation of the native Python version of IB API
Home-page: https://github.com/Devtography/ibpy_native
Author: Wing Chau @Devtography
Author-email: wing@devtography.com
License: UNKNOWN
Project-URL: Bug Reports, https://github.com/Devtography/ibpy_native/issues
Project-URL: Twitter, https://twitter.com/Devtography
Project-URL: Source, https://github.com/Devtography/ibpy_native/
Keywords: ibapi trading development
Platform: UNKNOWN
Classifier: Development Status :: 5 - Production/Stable
Classifier: Intended Audience :: Developers
Classifier: Topic :: Office/Business :: Financial :: Investment
Classifier: Topic :: Software Development :: Libraries
Classifier: License :: Free for non-commercial use
Classifier: Programming Language :: Python :: 3.7
Classifier: Programming Language :: Python :: 3.8
Classifier: Programming Language :: Python :: 3.9
Classifier: Intended Audience :: Financial and Insurance Industry
Classifier: Natural Language :: English
Classifier: Typing :: Typed
Requires-Python: >=3.7
Requires-Dist: deprecated (==1.2.11)
Requires-Dist: pytz (==2021.1)
Requires-Dist: typing-extensions (==3.7.4.3)
Requires-Dist: wrapt (==1.12.1)
Provides-Extra: dev
